fastlog/__init__.py
fastlog/__main__.py
fastlog/cli.py
fastlog/config.py
fastlog/core.py
fastlog/intercept.py
fastlog/log_handle.py
fastlog/monitor.py
fastlog/util.py
fastlog_io-0.2.4.dist-info/METADATA
fastlog_io-0.2.4.dist-info/WHEEL
fastlog_io-0.2.4.dist-info/entry_points.txt
fastlog_io-0.2.4.dist-info/licenses/LICENSE
fastlog_io-0.2.4.dist-info/RECORD
