Metadata-Version: 2.4
Name: fastlog-io
Version: 0.2.4
Summary: loguru fast wrapping supports fastapi
Author: owq
License: MIT License
License-File: LICENSE
Classifier: Development Status :: 2 - Pre-Alpha
Classifier: Operating System :: OS Independent
Classifier: Programming Language :: Python :: 3 :: Only
Classifier: Programming Language :: Python :: 3.10
Classifier: Programming Language :: Python :: 3.11
Classifier: Programming Language :: Python :: 3.12
Classifier: Programming Language :: Python :: Implementation :: CPython
Classifier: Topic :: System :: Logging
Requires-Python: >=3.10
Requires-Dist: fastnanoid==0.4.3
Requires-Dist: loguru>=0.7.3
